{
  "source": "/root/git/isolated/mycelium/crates/mycelium-doc/src/inline.rs",
  "emitted_items": [
    "MAX_DEPTH"
  ],
  "gaps": [
    {
      "file": "/root/git/isolated/mycelium/crates/mycelium-doc/src/inline.rs",
      "line": 29,
      "col": 1,
      "category": "GenericBound",
      "rust_construct": "GenericBound",
      "snippet": "# [doc = \" One inline span — a render-time view over a slice of the node's text (never an IR node).\"] # [derive (Debug , Clone , PartialEq , Eq)] pub enum Span < 'a > { # [doc = \" A literal text run (the emitter escapes it).\"] Text (& 'a str) , # [doc = \" Inline `` `code` `` — verbatim content (no nested parsing; the emitter escapes it).\"] Code (& 'a str) , # [doc = \" `**strong**` — bold, with parsed inner spans.\"] Strong (Vec < Span < 'a > >) , # [doc = \" `*em*` / `_em_` — emphasis, with parsed inner spans.\"] Em (Vec < Span < 'a > >) , # [doc = \" `[text](href)` — a link; `text` is parsed, `href` is the raw target (the emitter decides how\"] # [doc = \" to treat internal vs external — internal navigation is owned by the resolved `Xref` nodes).\"] Link { # [doc = \" The parsed link text.\"] text : Vec < Span < 'a > > , # [doc = \" The raw href/target (a `\\\"title\\\"` suffix already stripped).\"] href : & 'a str , } , }",
      "reason": "lifetime parameter `'a` has no grammar surface",
      "item_name": "Span"
    },
    {
      "file": "/root/git/isolated/mycelium/crates/mycelium-doc/src/inline.rs",
      "line": 50,
      "col": 1,
      "category": "GenericBound",
      "rust_construct": "GenericBound",
      "snippet": "# [doc = \" Parse `text` into inline spans (the subset in the module docs). Total over the input: every byte\"] # [doc = \" appears in exactly one span's text (never dropped, never duplicated).\"] # [must_use] pub fn parse (text : & str) -> Vec < Span < '_ > > { parse_spans (text , 0) }",
      "reason": "generic type path `Span < '_ >` — type argument `'_` is not a type (lifetime / const-generic / associated-type binding-or-constraint); `type_args` admits only type_refs, so left an explicit gap (VR-5)",
      "item_name": "parse"
    },
    {
      "file": "/root/git/isolated/mycelium/crates/mycelium-doc/src/inline.rs",
      "line": 57,
      "col": 1,
      "category": "GenericBound",
      "rust_construct": "GenericBound",
      "snippet": "fn parse_spans (text : & str , depth : u8) -> Vec < Span < '_ > > { let mut out = Vec :: new () ; if depth >= MAX_DEPTH { if ! text . is_empty () { out . push (Span :: Text (text)) ; } return out ; } let b = text . as_bytes () ; let mut i = 0 ; let mut lit = 0 ; while i < b . len () { let matched = match b [i] { b'`' => match_code (text , i) , b'*' if b . get (i + 1) == Some (& b'*') => match_strong (text , i , depth) , b'*' => match_em (text , i , b'*' , depth) , b'_' => match_em (text , i , b'_' , depth) , b'[' => match_link (text , i , depth) , _ => None , } ; if let Some ((span , end)) = matched { if lit < i { out . push (Span :: Text (& text [lit .. i])) ; } out . push (span) ; i = end ; lit = end ; } else { i = advance (text , i) ; } } if lit < b . len () { out . push (Span :: Text (& text [lit ..])) ; } out }",
      "reason": "generic type path `Span < '_ >` — type argument `'_` is not a type (lifetime / const-generic / associated-type binding-or-constraint); `type_args` admits only type_refs, so left an explicit gap (VR-5)",
      "item_name": "parse_spans"
    },
    {
      "file": "/root/git/isolated/mycelium/crates/mycelium-doc/src/inline.rs",
      "line": 94,
      "col": 1,
      "category": "Other",
      "rust_construct": "Other",
      "snippet": "# [doc = \" The next char boundary at/after `i` (UTF-8 safe single-char advance).\"] fn advance (text : & str , i : usize) -> usize { text [i ..] . chars () . next () . map_or (i + 1 , | c | i + c . len_utf8 ()) }",
      "reason": "method call `.map_or(...)` has no proven-emitted free-fn referent in this file (neither a D4-mangled inherent `Type__map_or` nor a bare inherent recorded by this file's left-to-right pass, nor a prim_map / combinator row). Emitting bare `map_or(recv, …)` would fabricate an unknown prim and file-poison myc-check (G-β Rank A / G2/VR-5; residual when the method body itself gapped — e.g. M-1037 `.to_vec()` inside `read_to_end` — so the declaration was never registered)",
      "item_name": "advance"
    },
    {
      "file": "/root/git/isolated/mycelium/crates/mycelium-doc/src/inline.rs",
      "line": 99,
      "col": 1,
      "category": "MultiStmtBody",
      "rust_construct": "MultiStmtBody",
      "snippet": "# [doc = \" The byte index just past the run of consecutive `delim` bytes starting at `start` (all ASCII).\"] fn delim_run_end (b : & [u8] , start : usize , delim : u8) -> usize { let mut k = start ; while k < b . len () && b [k] == delim { k += 1 ; } k }",
      "reason": "function body has a semicolon-terminated (value-discarding) statement expression before the tail — a `let`-chain body maps only simple `let x = e;` bindings plus a single trailing expression",
      "item_name": "delim_run_end"
    },
    {
      "file": "/root/git/isolated/mycelium/crates/mycelium-doc/src/inline.rs",
      "line": 108,
      "col": 1,
      "category": "GenericBound",
      "rust_construct": "GenericBound",
      "snippet": "# [doc = \" Inline code `` `...` `` — verbatim; no nested parsing (so `*`/`_` inside are not emphasis).\"] fn match_code (text : & str , i : usize) -> Option < (Span < '_ > , usize) > { let rel = text [i + 1 ..] . find ('`') ? ; let close = i + 1 + rel ; if close == i + 1 { return None ; } Some ((Span :: Code (& text [i + 1 .. close]) , close + 1)) }",
      "reason": "generic type path `Span < '_ >` — type argument `'_` is not a type (lifetime / const-generic / associated-type binding-or-constraint); `type_args` admits only type_refs, so left an explicit gap (VR-5)",
      "item_name": "match_code"
    },
    {
      "file": "/root/git/isolated/mycelium/crates/mycelium-doc/src/inline.rs",
      "line": 118,
      "col": 1,
      "category": "GenericBound",
      "rust_construct": "GenericBound",
      "snippet": "# [doc = \" `**strong**` — the inner is parsed; a code span inside is skipped when scanning for the closer.\"] fn match_strong (text : & str , i : usize , depth : u8) -> Option < (Span < '_ > , usize) > { let inner_start = i + 2 ; let close = find_closer (text , inner_start , \"**\") ? ; let inner = & text [inner_start .. close] ; if inner . is_empty () || inner . starts_with (' ') || inner . ends_with (' ') { return None ; } Some ((Span :: Strong (parse_spans (inner , depth + 1)) , close + 2)) }",
      "reason": "generic type path `Span < '_ >` — type argument `'_` is not a type (lifetime / const-generic / associated-type binding-or-constraint); `type_args` admits only type_refs, so left an explicit gap (VR-5)",
      "item_name": "match_strong"
    },
    {
      "file": "/root/git/isolated/mycelium/crates/mycelium-doc/src/inline.rs",
      "line": 129,
      "col": 1,
      "category": "GenericBound",
      "rust_construct": "GenericBound",
      "snippet": "# [doc = \" `*em*` / `_em_` — single-delimiter emphasis with flanking rules; `_` never opens intra-word.\"] fn match_em (text : & str , i : usize , delim : u8 , depth : u8) -> Option < (Span < '_ > , usize) > { let b = text . as_bytes () ; let next = * b . get (i + 1) ? ; if next . is_ascii_whitespace () { return None ; } if delim == b'_' && i > 0 && b [i - 1] . is_ascii_alphanumeric () { return None ; } let mut j = i + 1 ; while j < b . len () { if b [j] == b'`' { if let Some (rel) = text [j + 1 ..] . find ('`') { j = j + 1 + rel + 1 ; continue ; } } if b [j] == delim { let run = delim_run_end (b , j , delim) ; if run - j >= 2 { j = run ; continue ; } let prev = b [j - 1] ; let closer_ok = ! (prev . is_ascii_whitespace () || delim == b'_' && b . get (j + 1) . is_some_and (u8 :: is_ascii_alphanumeric)) ; if closer_ok { let inner = & text [i + 1 .. j] ; if inner . is_empty () { return None ; } return Some ((Span :: Em (parse_spans (inner , depth + 1)) , j + 1)) ; } } j = advance (text , j) ; } None }",
      "reason": "generic type path `Span < '_ >` — type argument `'_` is not a type (lifetime / const-generic / associated-type binding-or-constraint); `type_args` admits only type_refs, so left an explicit gap (VR-5)",
      "item_name": "match_em"
    },
    {
      "file": "/root/git/isolated/mycelium/crates/mycelium-doc/src/inline.rs",
      "line": 176,
      "col": 1,
      "category": "GenericBound",
      "rust_construct": "GenericBound",
      "snippet": "# [doc = \" `[text](href)` — text is parsed, href is the raw target (a `\\\"title\\\"` suffix stripped). The closing\"] # [doc = \" `]` is matched with **bracket-depth tracking**, so link text may itself contain balanced brackets\"] # [doc = \" (`[List[0]](url)` → text `List[0]`); genuinely unbalanced bracket text finds no matching `]` and is\"] # [doc = \" left fully literal rather than cut at the wrong bracket (G2 — never mis-parse).\"] fn match_link (text : & str , i : usize , depth : u8) -> Option < (Span < '_ > , usize) > { let close_br = matching_bracket (text , i) ? ; if text . as_bytes () . get (close_br + 1) != Some (& b'(') { return None ; } let href_start = close_br + 2 ; let close_paren_rel = text [href_start ..] . find (')') ? ; let close_paren = href_start + close_paren_rel ; let link_text = & text [i + 1 .. close_br] ; let href = text [href_start .. close_paren] . split_whitespace () . next () . unwrap_or (\"\") ; Some ((Span :: Link { text : parse_spans (link_text , depth + 1) , href , } , close_paren + 1 ,)) }",
      "reason": "generic type path `Span < '_ >` — type argument `'_` is not a type (lifetime / const-generic / associated-type binding-or-constraint); `type_args` admits only type_refs, so left an explicit gap (VR-5)",
      "item_name": "match_link"
    },
    {
      "file": "/root/git/isolated/mycelium/crates/mycelium-doc/src/inline.rs",
      "line": 203,
      "col": 1,
      "category": "Other",
      "rust_construct": "Other",
      "snippet": "# [doc = \" The byte index of the `]` that matches the `[` at `open` (bracket-depth balanced), or `None` if\"] # [doc = \" unbalanced. Inline code spans are skipped so a `[`/`]` inside backticks does not perturb the depth.\"] fn matching_bracket (text : & str , open : usize) -> Option < usize > { let b = text . as_bytes () ; let mut depth = 0i32 ; let mut j = open ; while j < b . len () { match b [j] { b'`' => { if let Some (rel) = text [j + 1 ..] . find ('`') { j = j + 1 + rel + 1 ; continue ; } } b'[' => depth += 1 , b']' => { depth -= 1 ; if depth == 0 { return Some (j) ; } } _ => { } } j = advance (text , j) ; } None }",
      "reason": "method call `.as_bytes(...)` has no proven-emitted free-fn referent in this file (neither a D4-mangled inherent `Type__as_bytes` nor a bare inherent recorded by this file's left-to-right pass, nor a prim_map / combinator row). Emitting bare `as_bytes(recv, …)` would fabricate an unknown prim and file-poison myc-check (G-β Rank A / G2/VR-5; residual when the method body itself gapped — e.g. M-1037 `.to_vec()` inside `read_to_end` — so the declaration was never registered)",
      "item_name": "matching_bracket"
    },
    {
      "file": "/root/git/isolated/mycelium/crates/mycelium-doc/src/inline.rs",
      "line": 231,
      "col": 1,
      "category": "Other",
      "rust_construct": "Other",
      "snippet": "# [doc = \" The byte offset of the closing `delim` (a 2-char marker like `**`) at/after `from`, skipping any\"] # [doc = \" inline code span so a marker inside backticks is not a closer. `None` if unbalanced.\"] fn find_closer (text : & str , from : usize , delim : & str) -> Option < usize > { let b = text . as_bytes () ; let dbytes = delim . as_bytes () ; let mut j = from ; while j + dbytes . len () <= b . len () { if b [j] == b'`' { if let Some (rel) = text [j + 1 ..] . find ('`') { j = j + 1 + rel + 1 ; continue ; } } if & b [j .. j + dbytes . len ()] == dbytes { return Some (j) ; } j = advance (text , j) ; } None }",
      "reason": "method call `.as_bytes(...)` has no proven-emitted free-fn referent in this file (neither a D4-mangled inherent `Type__as_bytes` nor a bare inherent recorded by this file's left-to-right pass, nor a prim_map / combinator row). Emitting bare `as_bytes(recv, …)` would fabricate an unknown prim and file-poison myc-check (G-β Rank A / G2/VR-5; residual when the method body itself gapped — e.g. M-1037 `.to_vec()` inside `read_to_end` — so the declaration was never registered)",
      "item_name": "find_closer"
    },
    {
      "file": "/root/git/isolated/mycelium/crates/mycelium-doc/src/inline.rs",
      "line": 252,
      "col": 1,
      "category": "Other",
      "rust_construct": "Other",
      "snippet": "# [doc = \" Whether a link `href` is an external target the inline renderer should link directly. Internal /\"] # [doc = \" relative links are owned by the resolved `Xref` sibling nodes (the inline renderer emits only the\"] # [doc = \" link *text* for them, so it never produces a dead link to a raw `.md` path).\"] # [must_use] pub fn is_external (href : & str) -> bool { href . starts_with (\"http://\") || href . starts_with (\"https://\") || href . starts_with (\"mailto:\") }",
      "reason": "method call `.starts_with(...)` has no proven-emitted free-fn referent in this file (neither a D4-mangled inherent `Type__starts_with` nor a bare inherent recorded by this file's left-to-right pass, nor a prim_map / combinator row). Emitting bare `starts_with(recv, …)` would fabricate an unknown prim and file-poison myc-check (G-β Rank A / G2/VR-5; residual when the method body itself gapped — e.g. M-1037 `.to_vec()` inside `read_to_end` — so the declaration was never registered)",
      "item_name": "is_external"
    },
    {
      "file": "/root/git/isolated/mycelium/crates/mycelium-doc/src/inline.rs",
      "line": 260,
      "col": 1,
      "category": "MultiStmtBody",
      "rust_construct": "MultiStmtBody",
      "snippet": "# [doc = \" Strip inline markdown from `text`, returning **plain, unescaped** text — formatting markers and\"] # [doc = \" link syntax removed, code/link text kept. For nav labels / a `<title>` / a JSON search field where\"] # [doc = \" literal `**`/backticks would leak (the emitter HTML-escapes for an HTML context; a JSON context is\"] # [doc = \" escaped by the serializer). E.g. ``\\\"DN-102 · The `?` Try-Operator\\\"`` → `\\\"DN-102 · The ? Try-Operator\\\"`.\"] # [must_use] pub fn to_plain (text : & str) -> String { fn walk (spans : & [Span < '_ >] , out : & mut String) { for span in spans { match span { Span :: Text (t) | Span :: Code (t) => out . push_str (t) , Span :: Strong (inner) | Span :: Em (inner) => walk (inner , out) , Span :: Link { text , .. } => walk (text , out) , } } } let mut out = String :: new () ; walk (& parse (text) , & mut out) ; out }",
      "reason": "function body contains a nested item declaration (e.g. a local `static`/`const`/`fn`) — this grammar fragment has no local-item production; only simple `let x = e;` bindings plus a trailing expression map",
      "item_name": "to_plain"
    }
  ],
  "total_top_level_items": 14
}