{
  "source": "/root/git/isolated/mycelium/crates/mycelium-doc/src/theme.rs",
  "emitted_items": [],
  "gaps": [
    {
      "file": "/root/git/isolated/mycelium/crates/mycelium-doc/src/theme.rs",
      "line": 24,
      "col": 1,
      "category": "Other",
      "rust_construct": "Other",
      "snippet": "# [doc = \" The shared, self-contained stylesheet (the one reviewed template's CSS, §5). Embedded inline in\"] # [doc = \" every page; fetches nothing. Feeds the pinned template hash recorded in each corpus-page footer\"] # [doc = \" (provenance, §6) via [`crate::emit::html::template_hash`].\"] # [doc = \"\"] # [doc = \" **Design system (reviewed reference).** The palette is Mycelium's guarantee lattice made visual —\"] # [doc = \" `moss` = Exact/Proven (primary accent, active nav), `amber` = Empirical (the \\\"✓ checked\\\" badge),\"] # [doc = \" `clay` = Declared (dead-xref strike, warnings), `ink-blue` = links/strings. Components are styled\"] # [doc = \" **through the tokens**, never with ad-hoc colours. Light/dark are declared so the persisted toggle\"] # [doc = \" wins in both directions (`:root[data-theme=\\\"…\\\"]` overrides the `prefers-color-scheme` default).\"] pub const READING_CSS : & str = r#\"\n:root{\n  --paper:#ecefe4;--paper-2:#e0e5d7;--ink:#161911;--ink-soft:#353b2e;--dim:#5a6151;\n  --line:#cfd5c4;--line-soft:#dbe0d0;--moss:#386f4e;--moss-deep:#235035;--amber:#9c6c17;\n  --clay:#a94a34;--ink-blue:#345872;--code-bg:#e4e9d9;--code-edge:#cfd5c1;\n  --tok-kw:#235035;--tok-type:#6f5210;--tok-num:#96422b;--tok-str:#345872;\n  --tok-com:#767d6b;--tok-fn:#1f241b;--tok-op:#545b47;\n  --serif:\"Iowan Old Style\",\"Charter\",\"Palatino Linotype\",Palatino,Georgia,serif;\n  --sans:ui-sans-serif,system-ui,-apple-system,\"Segoe UI\",Roboto,sans-serif;\n  --mono:ui-monospace,\"Cascadia Code\",\"JetBrains Mono\",\"SF Mono\",\"Source Code Pro\",Menlo,Consolas,monospace;\n  --measure:68ch;--sidebar-w:16rem;--toc-w:14rem;\n}\n:root[data-theme=\"light\"]{\n  --paper:#ecefe4;--paper-2:#e0e5d7;--ink:#161911;--ink-soft:#353b2e;--dim:#5a6151;\n  --line:#cfd5c4;--line-soft:#dbe0d0;--moss:#386f4e;--moss-deep:#235035;--amber:#9c6c17;\n  --clay:#a94a34;--ink-blue:#345872;--code-bg:#e4e9d9;--code-edge:#cfd5c1;\n  --tok-kw:#235035;--tok-type:#6f5210;--tok-num:#96422b;--tok-str:#345872;\n  --tok-com:#767d6b;--tok-fn:#1f241b;--tok-op:#545b47;\n}\n:root[data-theme=\"dark\"]{\n  --paper:#14160f;--paper-2:#1b1e16;--ink:#e6e9dd;--ink-soft:#c3c8b6;--dim:#8b917f;\n  --line:#2b2f24;--line-soft:#23271d;--moss:#74c091;--moss-deep:#59a074;--amber:#d9a648;\n  --clay:#e08a6f;--ink-blue:#86b4cf;--code-bg:#1b1e16;--code-edge:#2b2f24;\n  --tok-kw:#74c091;--tok-type:#d9a648;--tok-num:#e5926f;--tok-str:#86b4cf;\n  --tok-com:#7f8873;--tok-fn:#e6e9dd;--tok-op:#a9b09a;\n}\n@media (prefers-color-scheme: dark){\n  :root{\n    --paper:#14160f;--paper-2:#1b1e16;--ink:#e6e9dd;--ink-soft:#c3c8b6;--dim:#8b917f;\n    --line:#2b2f24;--line-soft:#23271d;--moss:#74c091;--moss-deep:#59a074;--amber:#d9a648;\n    --clay:#e08a6f;--ink-blue:#86b4cf;--code-bg:#1b1e16;--code-edge:#2b2f24;\n    --tok-kw:#74c091;--tok-type:#d9a648;--tok-num:#e5926f;--tok-str:#86b4cf;\n    --tok-com:#7f8873;--tok-fn:#e6e9dd;--tok-op:#a9b09a;\n  }\n}\n*{box-sizing:border-box}\nhtml{scroll-behavior:smooth}\nbody{\n  margin:0;font-family:var(--serif);font-size:1.0625rem;line-height:1.68;\n  color:var(--ink);background:var(--paper);\n  -webkit-font-smoothing:antialiased;text-rendering:optimizeLegibility;\n}\n::selection{background:color-mix(in srgb,var(--moss) 22%,transparent)}\na{color:var(--ink-blue);text-decoration-thickness:.06em;text-underline-offset:.15em}\na:hover{text-decoration-color:var(--moss)}\na.unresolved{color:var(--clay);text-decoration:line-through}\n:focus-visible{outline:2px solid var(--moss);outline-offset:2px;border-radius:3px}\n.skip-link{position:absolute;left:-999px;top:0;background:var(--moss);color:#fff;\n  font-family:var(--sans);padding:.5rem .9rem;border-radius:0 0 6px 0;z-index:20}\n.skip-link:focus{left:0}\n/* page frame */\n.site-header{border-bottom:1px solid var(--line);background:var(--paper-2);\n  position:sticky;top:0;z-index:10}\n.site-header .bar{max-width:82rem;margin:0 auto;padding:.7rem 1.25rem;\n  display:flex;align-items:center;gap:1rem}\n.site-header .site-title{font-family:var(--sans);font-size:1.02rem;margin:0;font-weight:650;\n  letter-spacing:-.01em}\n.site-header .tagline{font-family:var(--sans);color:var(--dim);font-size:.82rem;margin:0;flex:1;\n  min-width:0;overflow:hidden;text-overflow:ellipsis;white-space:nowrap}\n.theme-toggle{cursor:pointer;border:1px solid var(--line);background:var(--paper);\n  color:var(--ink);border-radius:8px;padding:.35rem .6rem;font-size:.95rem;line-height:1}\n.theme-toggle:hover{border-color:var(--moss)}\n.layout{max-width:82rem;margin:0 auto;display:grid;\n  grid-template-columns:var(--sidebar-w) minmax(0,1fr) var(--toc-w);\n  gap:1.6rem;padding:0 1.25rem;align-items:start}\n.layout.no-toc{grid-template-columns:var(--sidebar-w) minmax(0,1fr)}\n.sidebar,.on-this-page{position:sticky;top:4.2rem;max-height:calc(100vh - 5rem);\n  overflow:auto;padding:1.3rem 0;font-family:var(--sans);font-size:.9rem}\n.sidebar{border-right:1px solid var(--line)}\nmain{padding:1.5rem 0 3.5rem;min-width:0;max-width:var(--measure);margin:0 auto}\n/* sidebar nav tree */\n.nav-search{width:100%;padding:.5rem .6rem;font-family:var(--sans);font-size:.9rem;\n  border:1px solid var(--line);border-radius:8px;background:var(--paper);color:var(--ink);\n  margin-bottom:.6rem}\n.nav-search:focus{outline:2px solid var(--moss);border-color:var(--moss)}\n.search-results{list-style:none;margin:.3rem 0 .8rem;padding:0}\n.search-results li{margin:.15rem 0}\n.search-results a{display:block;padding:.25rem .4rem;border-radius:6px;text-decoration:none;\n  color:var(--ink)}\n.search-results a:hover{background:var(--paper-2)}\n.search-results .hint,.search-results .empty{color:var(--dim);font-size:.82rem;padding:.25rem .4rem}\n.nav-group{margin:.95rem 0 .2rem;font-size:.7rem;font-weight:700;letter-spacing:.1em;\n  text-transform:uppercase;color:var(--dim)}\n.sidebar ul{list-style:none;margin:0;padding:0}\n/* collapsible family/topic groups (native details/summary — no JS) */\n.sidebar details{margin:.05rem 0}\n.sidebar summary{cursor:pointer;list-style:none;display:flex;align-items:center;gap:.35rem;\n  padding:.28rem .4rem;border-radius:6px;font-size:.82rem;font-weight:600;color:var(--ink-soft)}\n.sidebar summary::-webkit-details-marker{display:none}\n.sidebar summary::before{content:\"\\25b8\";color:var(--dim);font-size:.7em;display:inline-block;\n  transition:transform .12s}\n.sidebar details[open]>summary::before{transform:rotate(90deg)}\n.sidebar summary:hover{background:var(--paper-2);color:var(--ink)}\n.sidebar summary:focus-visible{outline:2px solid var(--moss);outline-offset:1px}\n.sidebar .count{margin-left:auto;font-size:.72rem;font-weight:500;color:var(--dim);\n  font-variant-numeric:tabular-nums}\n.sidebar details>ul{margin:.05rem 0 .3rem .55rem;padding-left:.35rem;\n  border-left:1px solid var(--line-soft)}\n.sidebar li a{display:block;padding:.15rem .45rem;border-radius:6px;color:var(--ink-soft);\n  text-decoration:none;border-left:2px solid transparent;font-size:.82rem;line-height:1.35;\n  white-space:nowrap;overflow:hidden;text-overflow:ellipsis}\n.sidebar li a:hover{background:var(--paper-2);color:var(--ink)}\n.sidebar li a[aria-current=\"page\"]{color:var(--moss-deep);font-weight:600;\n  border-left-color:var(--moss);background:var(--paper-2)}\n/* on this page */\n.toc-title,.nav-title{font-size:.7rem;font-weight:700;letter-spacing:.1em;text-transform:uppercase;\n  color:var(--dim);margin:0 0 .4rem}\n.on-this-page ul{list-style:none;margin:0;padding:0}\n.on-this-page a{display:block;padding:.16rem 0;color:var(--dim);text-decoration:none;\n  border-left:2px solid var(--line);padding-left:.7rem}\n.on-this-page a:hover{color:var(--ink);border-left-color:var(--moss)}\n.on-this-page .lvl-3{padding-left:1.4rem}\n.on-this-page .lvl-4{padding-left:2.1rem}\n/* reading typography (serif body + headings) */\nh1,h2,h3,h4,h5,h6{font-family:var(--serif);line-height:1.24;font-weight:600;\n  margin:1.9em 0 .55em;scroll-margin-top:4.6rem}\nh1{font-size:2.15rem;margin-top:.2em;letter-spacing:-.018em;text-wrap:balance}\nh2{font-size:1.5rem;margin-top:1.7em;padding-top:.9rem;border-top:1px solid var(--line-soft)}\nh3{font-size:1.22rem}h4{font-size:1.06rem}h5,h6{font-size:.96rem;color:var(--ink-soft)}\np{margin:0 0 1.05em}\nul,ol{margin:0 0 1.05em;padding-left:1.4em}li{margin:.28em 0}\nmain>article>section{margin-bottom:.5rem}\nblockquote{margin:1.2em 0;padding:.2em 1em;border-left:3px solid var(--line);color:var(--ink-soft)}\nhr{border:0;border-top:1px solid var(--line);margin:2em 0}\n/* code */\ncode{font-family:var(--mono);font-size:.86em}\n:not(pre)>code{background:var(--code-bg);padding:.12em .35em;border-radius:5px;\n  border:1px solid var(--code-edge)}\npre{background:var(--code-bg);border:1px solid var(--code-edge);padding:.85rem 1rem;\n  border-radius:10px;overflow-x:auto;line-height:1.6;margin:0 0 1.15em}\npre code{background:none;border:0;padding:0;font-size:.86rem}\nfigure{margin:0 0 1.25em}\nfigure>.checked,figure>.level{display:inline-flex;align-items:center;margin-bottom:.4rem}\n/* syntax tokens (lexical only — Empirical/Declared; only fn-position idents are distinguished) */\n.tok-kw{color:var(--tok-kw);font-weight:600}\n.tok-type{color:var(--tok-type)}\n.tok-num{color:var(--tok-num)}\n.tok-str{color:var(--tok-str)}\n.tok-com{color:var(--tok-com);font-style:italic}\n.tok-fn{color:var(--tok-fn);font-weight:600}\n.tok-op{color:var(--tok-op)}\n/* comfortable tables (the corpus is table-heavy) — own scroll container */\n.table-wrap{overflow-x:auto;margin:0 0 1.25em;border:1px solid var(--line);border-radius:10px}\ntable{border-collapse:collapse;width:100%;font-size:.95rem}\nthead th{font-family:var(--sans);background:var(--paper-2);text-align:left;font-weight:640;\n  font-size:.86rem;letter-spacing:.01em}\nth,td{padding:.5rem .8rem;border-bottom:1px solid var(--line);vertical-align:top}\ntbody tr:nth-child(even){background:var(--paper-2)}\ntbody tr:last-child td{border-bottom:0}\n/* guarantee chips + markers (pill, sans, leading dot, lattice-tinted) */\n.level,.checked{font-family:var(--sans);font-size:.72rem;line-height:1.4;border-radius:999px;\n  padding:.06rem .55rem .06rem .5rem;letter-spacing:.02em;text-transform:none}\n.level::before,.checked::before{content:\"\\2022\";margin-right:.32rem;font-size:.9em}\n.level{color:var(--dim);background:color-mix(in srgb,var(--dim) 12%,transparent);\n  border:1px solid color-mix(in srgb,var(--dim) 34%,transparent)}\n.checked{color:var(--amber);background:color-mix(in srgb,var(--amber) 13%,transparent);\n  border:1px solid color-mix(in srgb,var(--amber) 40%,transparent)}\n.undocumented{color:var(--ink-soft);font-style:italic;border-left:3px solid var(--clay);\n  padding-left:.6rem}\n/* book chrome */\n.crumb{font-family:var(--sans);font-size:.85rem;color:var(--dim);margin:.2rem 0 1rem}\n.pager{display:flex;justify-content:space-between;gap:1rem;margin:2.6rem 0 0;\n  font-family:var(--sans);font-size:.9rem}\n.pager a{border:1px solid var(--line);border-radius:10px;padding:.55rem .9rem;\n  text-decoration:none;color:var(--ink);background:var(--paper-2)}\n.pager a:hover{border-color:var(--moss)}\n#book-search-box{width:100%;padding:.6rem .7rem;font-family:var(--sans);font-size:1rem;\n  border:1px solid var(--line);border-radius:10px;background:var(--paper);color:var(--ink)}\n#book-search-results{list-style:none;padding:0}#book-search-results li{margin:.5rem 0}\nfooter{font-family:var(--sans);color:var(--dim);font-size:.84rem;border-top:1px solid var(--line);\n  margin:2.5rem auto 0;padding:1.2rem 1.25rem;max-width:82rem}\n/* responsive: fold the rails away on narrow screens */\n@media (max-width:60rem){\n  .layout,.layout.no-toc{grid-template-columns:minmax(0,1fr)}\n  .on-this-page{display:none}\n  .sidebar{position:static;max-height:none;border-right:0;border-bottom:1px solid var(--line);top:0}\n}\n@media (prefers-reduced-motion: reduce){html{scroll-behavior:auto}}\n\"# ;",
      "reason": "top-level `const READING_CSS` — co-emit (ORACLE-R1 A4) only covers plain unsigned integer types (`u8`/`u16`/`u32`/`u64`/`u128`/`usize`); other types have no const item production and no faithful zero-arg-fn encoding (gap, never fabricate)",
      "item_name": "READING_CSS"
    },
    {
      "file": "/root/git/isolated/mycelium/crates/mycelium-doc/src/theme.rs",
      "line": 213,
      "col": 1,
      "category": "Other",
      "rust_construct": "Other",
      "snippet": "# [doc = \" The `<head>` theme bootstrap — runs **before first paint** so the correct palette is applied with\"] # [doc = \" no flash-of-wrong-theme. Reads the persisted choice; when unset it leaves `data-theme` off so the\"] # [doc = \" CSS `prefers-color-scheme` default governs (never-silent: an unreadable `localStorage` is caught\"] # [doc = \" and simply falls back to the media-query default).\"] pub const HEAD_THEME_INIT : & str = r#\"<script>\n(function(){try{var t=localStorage.getItem('myc-theme');\nif(t==='dark'||t==='light'){document.documentElement.setAttribute('data-theme',t);}}\ncatch(e){}})();\n</script>\"# ;",
      "reason": "top-level `const HEAD_THEME_INIT` — co-emit (ORACLE-R1 A4) only covers plain unsigned integer types (`u8`/`u16`/`u32`/`u64`/`u128`/`usize`); other types have no const item production and no faithful zero-arg-fn encoding (gap, never fabricate)",
      "item_name": "HEAD_THEME_INIT"
    },
    {
      "file": "/root/git/isolated/mycelium/crates/mycelium-doc/src/theme.rs",
      "line": 223,
      "col": 1,
      "category": "Other",
      "rust_construct": "Other",
      "snippet": "# [doc = \" The theme-toggle button (goes in the header bar). Wired by [`THEME_TOGGLE_JS`].\"] pub const THEME_TOGGLE_BUTTON : & str = \"<button class=\\\"theme-toggle\\\" id=\\\"theme-toggle\\\" type=\\\"button\\\" \\\n     aria-label=\\\"Toggle light or dark theme\\\" title=\\\"Toggle light/dark\\\">\\u{25d0}</button>\" ;",
      "reason": "top-level `const THEME_TOGGLE_BUTTON` — co-emit (ORACLE-R1 A4) only covers plain unsigned integer types (`u8`/`u16`/`u32`/`u64`/`u128`/`usize`); other types have no const item production and no faithful zero-arg-fn encoding (gap, never fabricate)",
      "item_name": "THEME_TOGGLE_BUTTON"
    },
    {
      "file": "/root/git/isolated/mycelium/crates/mycelium-doc/src/theme.rs",
      "line": 228,
      "col": 1,
      "category": "Other",
      "rust_construct": "Other",
      "snippet": "# [doc = \" Wires [`THEME_TOGGLE_BUTTON`]: flips the *effective* theme (honouring the OS default when no\"] # [doc = \" choice is stored yet) and persists it. Placed at end-of-body.\"] pub const THEME_TOGGLE_JS : & str = r#\"<script>\n(function(){\n  var btn=document.getElementById('theme-toggle');\n  if(!btn)return;\n  function effective(){\n    var a=document.documentElement.getAttribute('data-theme');\n    if(a)return a;\n    return window.matchMedia&&window.matchMedia('(prefers-color-scheme: dark)').matches?'dark':'light';\n  }\n  btn.addEventListener('click',function(){\n    var next=effective()==='dark'?'light':'dark';\n    document.documentElement.setAttribute('data-theme',next);\n    try{localStorage.setItem('myc-theme',next);}catch(e){}\n  });\n})();\n</script>\"# ;",
      "reason": "top-level `const THEME_TOGGLE_JS` — co-emit (ORACLE-R1 A4) only covers plain unsigned integer types (`u8`/`u16`/`u32`/`u64`/`u128`/`usize`); other types have no const item production and no faithful zero-arg-fn encoding (gap, never fabricate)",
      "item_name": "THEME_TOGGLE_JS"
    },
    {
      "file": "/root/git/isolated/mycelium/crates/mycelium-doc/src/theme.rs",
      "line": 247,
      "col": 1,
      "category": "Other",
      "rust_construct": "Other",
      "snippet": "# [doc = \" The corpus-site client-side search: a small substring/prefix filter over the already-emitted\"] # [doc = \" `search-index.jsonl` (one JSON record per node — [`crate::emit::json`]). No new dependency, no\"] # [doc = \" search engine; fetched relative to `window.MYC_BASE` (`\\\"\\\"` on the index, `\\\"../\\\"` on a page).\"] # [doc = \"\"] # [doc = \" Never-silent (G2): a failed `fetch` (e.g. opened over `file://` where the browser blocks it)\"] # [doc = \" shows an explicit hint rather than a silently-dead box — the honest degradation, the same posture\"] # [doc = \" as the rest of this crate. Only records that carry a `title` (documents/sections — the meaningful\"] # [doc = \" navigation targets) are surfaced; matching is case-insensitive over title + anchor.\"] pub const CORPUS_SEARCH_JS : & str = r#\"<script>\n(function(){\n  var box=document.getElementById('corpus-search-box');\n  var out=document.getElementById('corpus-search-results');\n  if(!box||!out)return;\n  var base=window.MYC_BASE||'';\n  var records=null,loadErr=false;\n  function docOf(a){var i=a.indexOf('--');return i<0?a:a.slice(0,i);}\n  function load(){\n    return fetch(base+'search-index.jsonl').then(function(r){return r.text();}).then(function(t){\n      records=t.split('\\n').filter(Boolean).map(function(l){try{return JSON.parse(l);}catch(e){return null;}})\n        .filter(function(r){return r&&r.title;});\n    }).catch(function(){loadErr=true;});\n  }\n  function render(q){\n    out.innerHTML='';\n    if(loadErr){out.innerHTML='<li class=\"empty\">Search needs the site served over http:// (fetch is blocked on file://).</li>';return;}\n    if(records===null){out.innerHTML='<li class=\"hint\">Loading index…</li>';return;}\n    q=(q||'').trim().toLowerCase();\n    if(!q){return;}\n    var hits=records.filter(function(r){\n      return r.title.toLowerCase().indexOf(q)>=0||(r.anchor||'').toLowerCase().indexOf(q)>=0;\n    }).slice(0,40);\n    if(hits.length===0){out.innerHTML='<li class=\"empty\">No matches.</li>';return;}\n    hits.forEach(function(r){\n      var li=document.createElement('li');var a=document.createElement('a');\n      a.href=base+'pages/'+docOf(r.anchor)+'.html#'+r.anchor;\n      a.textContent=r.title;a.setAttribute('data-kind',r.kind||'');\n      li.appendChild(a);out.appendChild(li);\n    });\n  }\n  box.addEventListener('input',function(){\n    if(records===null&&!loadErr){load().then(function(){render(box.value);});}\n    else{render(box.value);}\n  });\n  box.addEventListener('focus',function(){if(records===null&&!loadErr){load();}});\n})();\n</script>\"# ;",
      "reason": "top-level `const CORPUS_SEARCH_JS` — co-emit (ORACLE-R1 A4) only covers plain unsigned integer types (`u8`/`u16`/`u32`/`u64`/`u128`/`usize`); other types have no const item production and no faithful zero-arg-fn encoding (gap, never fabricate)",
      "item_name": "CORPUS_SEARCH_JS"
    },
    {
      "file": "/root/git/isolated/mycelium/crates/mycelium-doc/src/theme.rs",
      "line": 294,
      "col": 1,
      "category": "Other",
      "rust_construct": "Other",
      "snippet": "# [doc = \" The skip-to-content link (accessibility — first focusable element).\"] pub const SKIP_LINK : & str = \"<a class=\\\"skip-link\\\" href=\\\"#content\\\">Skip to content</a>\" ;",
      "reason": "top-level `const SKIP_LINK` — co-emit (ORACLE-R1 A4) only covers plain unsigned integer types (`u8`/`u16`/`u32`/`u64`/`u128`/`usize`); other types have no const item production and no faithful zero-arg-fn encoding (gap, never fabricate)",
      "item_name": "SKIP_LINK"
    }
  ],
  "total_top_level_items": 6
}